ricomodels/__init__.py
ricomodels/backbones/mobilenetv2/mobilenet_v2.py
ricomodels/backbones/train_backbones.py
ricomodels/deeplabv3_plus/predict_deeplabv3_plus.py
ricomodels/resnet-50-pretrained.ipynb
ricomodels/seq2seq/dataload_seq2seq.py
ricomodels/seq2seq/seq2seq.py
ricomodels/seq2seq/spa-eng.txt
ricomodels/tests/test_dataloading.py
ricomodels/tests/test_losses.py
ricomodels/tests/test_training_tools.py
ricomodels/tests/test_visualization.py
ricomodels/unet/predict_unet.py
ricomodels/unet/train_unet.py
ricomodels/unet/unet.py
ricomodels/utils/data_loading.py
ricomodels/utils/google_drive_upload.py
ricomodels/utils/losses.py
ricomodels/utils/training_tools.py
ricomodels/utils/visualization.py
ricomodels/utils/weights_uploading.py
ricomodels/weights/resnet_cifar10.pth
ricomodels/weights/unet_pascal_9.pth
ricomodels-0.2.5.dist-info/WHEEL
ricomodels-0.2.5.dist-info/METADATA
ricomodels-0.2.5.dist-info/RECORD
